__init__.py
utils.py
mllux-0.0.1.dist-info/LICENSE
mllux-0.0.1.dist-info/METADATA
mllux-0.0.1.dist-info/WHEEL
mllux-0.0.1.dist-info/top_level.txt
mllux-0.0.1.dist-info/RECORD
