Metadata-Version: 2.1
Name: mllux
Version: 0.0.1
Summary: Machine Learning Luxoft Package
Author-email: Karl Mitri <karl.mitri@dxc.com>
Classifier: Programming Language :: Python :: 3
Classifier: License :: OSI Approved :: MIT License
Classifier: Operating System :: OS Independent
Requires-Python: >=3.7
License-File: LICENSE
